examples/__init__.py
examples/shakespeare.py
examples/var_eval.py
examples/var_rename.py
iluvattnshun/__init__.py
iluvattnshun/logger.py
iluvattnshun/nn.py
iluvattnshun/prompter.py
iluvattnshun/trainer.py
iluvattnshun/types.py
iluvattnshun/utils.py
iluvattnshun/viz.py
iluvattnshun-0.0.1.dist-info/METADATA
iluvattnshun-0.0.1.dist-info/WHEEL
iluvattnshun-0.0.1.dist-info/top_level.txt
iluvattnshun-0.0.1.dist-info/RECORD
