Metadata-Version: 2.4
Name: iluvattnshun
Version: 0.0.1
Summary: A framework for quick attention-based experiments.
Home-page: https://github.com/michael-lutz/iluvattnshun
Author: michael-lutz
Requires-Python: >=3.11
Requires-Dist: numpy
Requires-Dist: colorama
Requires-Dist: mypy
Requires-Dist: tensorboard
Requires-Dist: tensorflow
Requires-Dist: torch
Dynamic: author
Dynamic: description
Dynamic: description-content-type
Dynamic: home-page
Dynamic: requires-dist
Dynamic: requires-python
Dynamic: summary
